.DS_Store
pssmpro/.DS_Store
pssmpro/__init__.py
pssmpro/features.py
pssmpro/data/.DS_Store
pssmpro/data/__init__.py
pssmpro/data/example.fasta
pssmpro/data/pssm_files/__init__.py
pssmpro/data/pssm_files/example_1.pssm
pssmpro/data/pssm_files/example_2.pssm
pssmpro-0.0.2.dist-info/LICENSE
pssmpro-0.0.2.dist-info/METADATA
pssmpro-0.0.2.dist-info/WHEEL
pssmpro-0.0.2.dist-info/top_level.txt
pssmpro-0.0.2.dist-info/RECORD
