Metadata-Version: 2.1
Name: pssmpro
Version: 0.0.2
Summary: A python tool for numerically encoding protein sequences based on position specific scoring matrices
Home-page: https://github.com/deeprob/pssmpro.git
Author: Deepro Banerjee
Author-email: deepro.2.4@gmail.com
License: UNKNOWN
Platform: UNKNOWN
Classifier: Programming Language :: Python :: 3
Classifier: License :: OSI Approved :: MIT License
Classifier: Operating System :: OS Independent
Requires-Python: >=3.0
License-File: LICENSE
Requires-Dist: numpy
